{
  "TabPane/name":{
    "description": "用于标识当前面板，对应 value，默认为其索引值",
    "optionTyep": "String",
    "defaultValue": "-"
  },
  "TabPane/label":{
    "description": "选项卡头显示文字，支持 Render 函数。",
    "optionTyep": "String | Function",
    "defaultValue": "-"
  },
  "TabPane/icon":{
    "description": "选项卡图标",
    "optionTyep": "String",
    "defaultValue": "-"
  },
  "TabPane/disabled":{
    "description": "是否禁用该选项卡",
    "optionTyep": "Boolean",
    "defaultValue": "false"
  },
  "TabPane/closable":{
    "description": "是否可以关闭页签，仅在 type=card 时有效",
    "optionTyep": "Boolean",
    "defaultValue": "null"
  },
  "TabPane/tab":{
    "description": "当嵌套使用 Tabs，设置该属性指向对应 Tabs 的 name 字段",
    "optionTyep": "String",
    "defaultValue": "-"
  },
  "TabPane/index":{
    "description": "在 TabPane 使用 v-if 时，并不会按照预先的顺序渲染，这时可设置 index，并从小到大排序(需大于 0)",
    "optionTyep": "Number",
    "defaultValue": "-"
  }
}